amangee/__init__.py
amangee/ai.py
amangee/gee.py
amangee/hydrology.py
amangee-0.2.2.dist-info/METADATA
amangee-0.2.2.dist-info/WHEEL
amangee-0.2.2.dist-info/top_level.txt
amangee-0.2.2.dist-info/RECORD
