Metadata-Version: 2.1
Name: amangee
Version: 0.2.2
Summary: A Python library for GEE, AI, and hydrology applications.
Home-page: https://github.com/yourusername/amangee
Author: Chakapp
Author-email: chakapp2424@example.com
License: MIT
Keywords: hydrology gee ai watershed python geospatial
Platform: UNKNOWN
Classifier: Programming Language :: Python :: 3
Classifier: License :: OSI Approved :: MIT License
Classifier: Operating System :: OS Independent
Classifier: Development Status :: 3 - Alpha
Classifier: Topic :: Scientific/Engineering :: GIS
Classifier: Intended Audience :: Science/Research
Requires-Python: >=3.7
Requires-Dist: numpy
Requires-Dist: pandas
Requires-Dist: geopandas
Requires-Dist: folium
Requires-Dist: matplotlib
Requires-Dist: rasterio
Requires-Dist: shapely
Requires-Dist: scipy
Requires-Dist: pysheds
